MANIFEST.in
README.rst
requirements.txt
setup.py
version.txt
Tokage.egg-info/PKG-INFO
Tokage.egg-info/SOURCES.txt
Tokage.egg-info/dependency_links.txt
Tokage.egg-info/requires.txt
Tokage.egg-info/top_level.txt
tokage/__init__.py
tokage/anime.py
tokage/base.py
tokage/character.py
tokage/client.py
tokage/errors.py
tokage/manga.py
tokage/partial.py
tokage/person.py
tokage/utils.py