Metadata-Version: 1.0
Name: Tokage
Version: 1.4
Summary: Async wrapper for the MyAnimeList API
Home-page: https://gitlab.com/Synder/Tokage
Author: SynderBlack
Author-email: UNKNOWN
License: MIT
Platform: UNKNOWN
